gibberish_score/__init__.py
gibberish_score/gibberish_score.py
gibberish_score/model_builder.py
tests/__init__.py
tests/test_all.py
gibberish_score-0.1.7.dist-info/LICENSE
gibberish_score-0.1.7.dist-info/METADATA
gibberish_score-0.1.7.dist-info/WHEEL
gibberish_score-0.1.7.dist-info/top_level.txt
gibberish_score-0.1.7.dist-info/RECORD
